pattan_mongo_survey/__init__.py
pattan_mongo_survey/exceptions.py
pattan_mongo_survey/mongo.py
pattan_mongo_survey-1.1.2.dist-info/LICENSE
pattan_mongo_survey-1.1.2.dist-info/METADATA
pattan_mongo_survey-1.1.2.dist-info/WHEEL
pattan_mongo_survey-1.1.2.dist-info/top_level.txt
pattan_mongo_survey-1.1.2.dist-info/RECORD
