Metadata-Version: 2.2
Name: pattan-mongo-survey
Version: 1.1.2
Summary: Support a surveyJS frontend with a mongodb backend
Author-email: Markus Weltin <mweltin@pattan.net>
Maintainer-email: Markus Weltin <mweltin@pattan.net>
Project-URL: Homepage, https://github.com/pattan-net/pattan-mongo-survey
Project-URL: Important, https://www.youtube.com/watch?v=xvFZjo5PgG0
Project-URL: Documentation, https://github.com/pattan-net/pattan-mongo-survey/tree/main/docs
Keywords: mongo,surveyJS
Classifier: Programming Language :: Python :: 3
Classifier: License :: OSI Approved :: BSD License
Classifier: Operating System :: OS Independent
Requires-Python: >=3.10
License-File: LICENSE
Requires-Dist: pymongo>=4.8.0
